gsuitefy/__init__.py
gsuitefy/gsuite.py
gsuitefy-1.1.3.data/scripts/gsuitefy
gsuitefy-1.1.3.dist-info/LICENSE
gsuitefy-1.1.3.dist-info/METADATA
gsuitefy-1.1.3.dist-info/WHEEL
gsuitefy-1.1.3.dist-info/top_level.txt
gsuitefy-1.1.3.dist-info/RECORD
