Metadata-Version: 2.1
Name: gsuitefy
Version: 1.1.3
Summary: Gsuite Admin client to manage users and groups
Home-page: https://github.com/marcosvidolin/gsuitefy
Author: Marcos Alexandre Vidolin de Lima
Author-email: marcosvidolin@gmail.com
License: UNKNOWN
Platform: UNKNOWN
Classifier: Programming Language :: Python :: 2.7
Classifier: Programming Language :: Python :: 3.4
Classifier: Programming Language :: Python :: 3.5
Classifier: Programming Language :: Python :: 3.6
Classifier: Programming Language :: Python :: 3.7
Classifier: License :: OSI Approved :: MIT License
Classifier: Operating System :: OS Independent
Requires-Dist: google-api-python-client (==1.7.11)
Requires-Dist: google-auth-httplib2 (==0.0.3)
Requires-Dist: google-auth-oauthlib (==0.4.0)
Requires-Dist: oauth2client (==4.1.3)
